README.rst
setup.py
characterai/__init__.py
characterai/auth.py
characterai/errors.py
characterai.egg-info/PKG-INFO
characterai.egg-info/SOURCES.txt
characterai.egg-info/dependency_links.txt
characterai.egg-info/requires.txt
characterai.egg-info/top_level.txt
characterai/aiocai/__init__.py
characterai/aiocai/client.py
characterai/aiocai/methods/__init__.py
characterai/aiocai/methods/account.py
characterai/aiocai/methods/characters.py
characterai/aiocai/methods/chat1.py
characterai/aiocai/methods/chat2.py
characterai/aiocai/methods/chats.py
characterai/aiocai/methods/other.py
characterai/aiocai/methods/recent.py
characterai/aiocai/methods/users.py
characterai/aiocai/methods/utils.py
characterai/pycai/__init__.py
characterai/pycai/client.py
characterai/pycai/methods/__init__.py
characterai/pycai/methods/account.py
characterai/pycai/methods/characters.py
characterai/pycai/methods/chat1.py
characterai/pycai/methods/chat2.py
characterai/pycai/methods/chats.py
characterai/pycai/methods/other.py
characterai/pycai/methods/recent.py
characterai/pycai/methods/users.py
characterai/pycai/methods/utils.py
characterai/types/__init__.py
characterai/types/account.py
characterai/types/character.py
characterai/types/chat1.py
characterai/types/chat2.py
characterai/types/other.py
characterai/types/recent.py
characterai/types/user.py