Metadata-Version: 2.1
Name: characterai
Version: 1.0.1
Summary: An unofficial API for Character AI for Python
Home-page: https://github.com/kramcat/characterai
Author: kramcat
License: MIT
Project-URL: Community, https://discord.gg/ZHJe3tXQkf
Project-URL: Source, https://github.com/kramcat/characterai
Project-URL: Documentation, https://docs.kram.cat
Keywords: ai wrapper api library
Classifier: Programming Language :: Python :: 3.10
Classifier: License :: OSI Approved :: MIT License
Requires-Dist: pydantic
Requires-Dist: curl_cffi
Requires-Dist: websockets
